signalfx_lambda/__init__.py
signalfx_lambda/metrics.py
signalfx_lambda/tracing.py
signalfx_lambda/utils.py
signalfx_lambda/version.py
signalfx_lambda_ppiastucki-0.2.1.dist-info/LICENSE
signalfx_lambda_ppiastucki-0.2.1.dist-info/METADATA
signalfx_lambda_ppiastucki-0.2.1.dist-info/WHEEL
signalfx_lambda_ppiastucki-0.2.1.dist-info/top_level.txt
signalfx_lambda_ppiastucki-0.2.1.dist-info/zip-safe
signalfx_lambda_ppiastucki-0.2.1.dist-info/RECORD
