Metadata-Version: 2.1
Name: signalfx-lambda-ppiastucki
Version: 0.2.1
Summary: SignalFx Lambda Python Wrapper
Home-page: https://github.com/signalfx/lambda-python
Author: SignalFx, Inc
Author-email: info@signalfx.com
License: Apache Software License v2
Platform: UNKNOWN
Classifier: Operating System :: OS Independent
Classifier: Programming Language :: Python
Requires-Dist: signalfx (>=1.0.16)
Requires-Dist: sfx-jaeger-client (>=3.13.1.dev0)
Requires-Dist: six (>=1.4.0)
